CHANGES.rst
CONTRIBUTORS.rst
DEVELOP.rst
LICENSE.rst
MANIFEST.in
README.rst
setup.cfg
setup.py
docs/index.rst
src/rc/__init__.py
src/rc.customcontent.egg-info/PKG-INFO
src/rc.customcontent.egg-info/SOURCES.txt
src/rc.customcontent.egg-info/dependency_links.txt
src/rc.customcontent.egg-info/entry_points.txt
src/rc.customcontent.egg-info/namespace_packages.txt
src/rc.customcontent.egg-info/not-zip-safe
src/rc.customcontent.egg-info/requires.txt
src/rc.customcontent.egg-info/top_level.txt
src/rc/customcontent/__init__.py
src/rc/customcontent/configure.zcml
src/rc/customcontent/interfaces.py
src/rc/customcontent/permissions.zcml
src/rc/customcontent/setuphandlers.py
src/rc/customcontent/testing.py
src/rc/customcontent/upgrades.py
src/rc/customcontent/upgrades.zcml
src/rc/customcontent/browser/__init__.py
src/rc/customcontent/browser/configure.zcml
src/rc/customcontent/browser/overrides/.gitkeep
src/rc/customcontent/browser/overrides/plone.app.contenttypes.browser.templates.file.pt
src/rc/customcontent/browser/static/.gitkeep
src/rc/customcontent/locales/README.rst
src/rc/customcontent/locales/__init__.py
src/rc/customcontent/locales/rc.customcontent.pot
src/rc/customcontent/locales/update.py
src/rc/customcontent/locales/update.sh
src/rc/customcontent/locales/en/LC_MESSAGES/rc.customcontent.mo
src/rc/customcontent/locales/en/LC_MESSAGES/rc.customcontent.po
src/rc/customcontent/profiles/default/browserlayer.xml
src/rc/customcontent/profiles/default/catalog.xml
src/rc/customcontent/profiles/default/metadata.xml
src/rc/customcontent/profiles/default/registry.xml
src/rc/customcontent/profiles/default/rolemap.xml
src/rc/customcontent/profiles/uninstall/browserlayer.xml
src/rc/customcontent/tests/__init__.py
src/rc/customcontent/tests/test_robot.py
src/rc/customcontent/tests/test_setup.py
src/rc/customcontent/tests/robot/test_example.robot